README.md
setup.py
bin/aigui
bin/cmd_ai
cmd_ai/__init__.py
cmd_ai/api_key.py
cmd_ai/best_examples.py
cmd_ai/calc_budget.py
cmd_ai/config.py
cmd_ai/function_calendar.py
cmd_ai/function_chmi.py
cmd_ai/function_gmail.py
cmd_ai/function_goog.py
cmd_ai/function_nehody.py
cmd_ai/function_sympy.py
cmd_ai/function_webc.py
cmd_ai/g_ask_claude.py
cmd_ai/g_ask_gemini.py
cmd_ai/g_askdalle.py
cmd_ai/g_askme.py
cmd_ai/g_askvision.py
cmd_ai/key_enter.py
cmd_ai/operate_context_files.py
cmd_ai/pipe.py
cmd_ai/speak.py
cmd_ai/syscom.py
cmd_ai/texts.py
cmd_ai/topbar.py
cmd_ai/unitname.py
cmd_ai/version.py
cmd_ai.egg-info/PKG-INFO
cmd_ai.egg-info/SOURCES.txt
cmd_ai.egg-info/dependency_links.txt
cmd_ai.egg-info/requires.txt
cmd_ai.egg-info/top_level.txt