Metadata-Version: 2.1
Name: cmd-ai
Version: 0.7.3
Summary: Another ChatGTP project in commandline of linux
Home-page: http://gitlab.com/me/cmd_ai
Author: jaromrax
Author-email: jaromrax@gmail.com
License: GPL2
